doblib/__init__.py
doblib/__main__.py
doblib/action.py
doblib/aggregate.py
doblib/base.py
doblib/ci.py
doblib/env.py
doblib/freeze.py
doblib/migrate.py
doblib/module.py
doblib/run.py
doblib/utils.py
doblib_legacy-0.17.0.dist-info/LICENSE.md
doblib_legacy-0.17.0.dist-info/METADATA
doblib_legacy-0.17.0.dist-info/WHEEL
doblib_legacy-0.17.0.dist-info/entry_points.txt
doblib_legacy-0.17.0.dist-info/top_level.txt
doblib_legacy-0.17.0.dist-info/RECORD
