Metadata-Version: 2.1
Name: doblib-legacy
Version: 0.17.0
Summary: Management tool for Odoo installations
Home-page: https://github.com/initos/dob-lib
Author: initOS GmbH
Author-email: info@initos.com
License: Apache License 2.0
Keywords: odoo environment management
Platform: UNKNOWN
Classifier: Environment :: Console
Classifier: License :: OSI Approved :: Apache Software License
Classifier: Operating System :: OS Independent
Classifier: Programming Language :: Python :: 2
Requires-Python: <3.0
Requires-Dist: coverage
Requires-Dist: debugpy
Requires-Dist: flake8
Requires-Dist: git-aggregator
Requires-Dist: ipython
Requires-Dist: isort
Requires-Dist: mock
Requires-Dist: pylint-odoo (<2.0)
Requires-Dist: python-dateutil
Requires-Dist: pytest-cov
Requires-Dist: pytest-odoo
Requires-Dist: PyYAML
